{
    "fluentMethods": true,
    "relationships": [
        {
            "relationshipType": "many-to-one",
            "relationshipName": "marker",
            "otherEntityName": "marker",
            "otherEntityField": "id"
        },
        {
            "relationshipType": "many-to-one",
            "relationshipName": "route",
            "otherEntityName": "routeOne",
            "otherEntityField": "id"
        }
    ],
    "fields": [
        {
            "fieldName": "ordinal",
            "fieldType": "String"
        }
    ],
    "changelogDate": "20180404164555",
    "entityTableName": "control_point",
    "dto": "mapstruct",
    "pagination": "no",
    "service": "serviceImpl",
    "jpaMetamodelFiltering": false
}